aftershoq/__init__.py
aftershoq/interface/__init__.py
aftershoq/interface/ilqcl.py
aftershoq/interface/inegf.py
aftershoq/interface/inextnano.py
aftershoq/interface/interface.py
aftershoq/interface/isewlab.py
aftershoq/interface/isewself.py
aftershoq/interface/ndtestfunc.py
aftershoq/materials/__init__.py
aftershoq/materials/materials.py
aftershoq/numerics/GAopt.py
aftershoq/numerics/MDgauss.py
aftershoq/numerics/__init__.py
aftershoq/numerics/gaussopt.py
aftershoq/numerics/numerics.py
aftershoq/numerics/optimizer.py
aftershoq/numerics/paraopt.py
aftershoq/numerics/runplatf.py
aftershoq/qcls/__init__.py
aftershoq/qcls/qcls.py
aftershoq/structure/__init__.py
aftershoq/structure/classes.py
aftershoq/structure/sgenerator.py
aftershoq/utils/__init__.py
aftershoq/utils/chi3.py
aftershoq/utils/const.py
aftershoq/utils/debug.py
aftershoq/utils/hilbertutil.py
aftershoq/utils/systemutil.py
examples/QCLexample.py
examples/__init__.py
examples/example_chi2.py
examples/example_negf.py
examples/example_nextnano.py
examples/example_sewlab.py
examples/example_sewself.py
examples/test_AlInGaAs.py
examples/test_ZnO.py
examples/test_optim.py
hilbert_curve/__init__.py
hilbert_curve/examples.py
hilbert_curve/hilbert.py
hilbert_curve/make_anim_3d.py
hilbert_curve/make_image_2d.py
hilbert_curve/make_image_3d.py
hilbert_curve/test.py
qcls/__init__.py
qcls/detectors_faist.py
qcls/qcls_faist.py
aftershoq-1.0.dist-info/LICENSE
aftershoq-1.0.dist-info/METADATA
aftershoq-1.0.dist-info/WHEEL
aftershoq-1.0.dist-info/top_level.txt
aftershoq-1.0.dist-info/RECORD
