Metadata-Version: 2.1
Name: aftershoq
Version: 1.0
Summary: A Flexible Tool for QCL/QCD Opitmization
Home-page: https://github.com/mfranckie/aftershoq
Author: Martin Franckie
Author-email: martin.franckie@phys.ethz.ch
License: UNKNOWN
Platform: UNKNOWN
Classifier: Programming Language :: Python :: 3
Classifier: License :: OSI Approved :: GNU Library or Lesser General Public License (LGPL)
Classifier: Operating System :: OS Independent
Requires-Python: >=3.6
Requires-Dist: numpy
Requires-Dist: scipy
Requires-Dist: matplotlib
Requires-Dist: lxml
